{
  "daily": {
    "2026-04-13": {
      "unique_visitors": [
        "user_8e9xhfoz9_1775979675331",
        "user_aazl70g7k_1776027407849",
        "user_wfkjt6juo_1776076058238"
      ],
      "page_views": 11,
      "countries": {
        "india": 5,
        "vietnam": 4,
        "indonesia": 2
      },
      "categories": {
        "real_estate": 7,
        "realestate": 4
      },
      "hours": {
        "10": 11
      },
      "referrers": {},
      "devices": {
        "mobile": 5,
        "desktop": 6
      }
    }
  },
  "visitors": {
    "user_8e9xhfoz9_1775979675331": {
      "first_seen": "2026-04-13",
      "visits": 5,
      "last_seen": "2026-04-13"
    },
    "user_aazl70g7k_1776027407849": {
      "first_seen": "2026-04-13",
      "visits": 5,
      "last_seen": "2026-04-13"
    },
    "user_wfkjt6juo_1776076058238": {
      "first_seen": "2026-04-13",
      "visits": 1,
      "last_seen": "2026-04-13"
    }
  }
}